odoo/addons/stock_picking_auto_create_lot_sequence/README.rst
odoo/addons/stock_picking_auto_create_lot_sequence/__init__.py
odoo/addons/stock_picking_auto_create_lot_sequence/__manifest__.py
odoo/addons/stock_picking_auto_create_lot_sequence/i18n/it.po
odoo/addons/stock_picking_auto_create_lot_sequence/i18n/stock_picking_auto_create_lot_sequence.pot
odoo/addons/stock_picking_auto_create_lot_sequence/models/__init__.py
odoo/addons/stock_picking_auto_create_lot_sequence/models/stock_move_line.py
odoo/addons/stock_picking_auto_create_lot_sequence/readme/DESCRIPTION.rst
odoo/addons/stock_picking_auto_create_lot_sequence/static/description/icon.png
odoo/addons/stock_picking_auto_create_lot_sequence/static/description/index.html
odoo/addons/stock_picking_auto_create_lot_sequence/tests/__init__.py
odoo/addons/stock_picking_auto_create_lot_sequence/tests/test_stock_picking_auto_create_lot_sequence.py
odoo_addon_stock_picking_auto_create_lot_sequence-16.0.1.0.0.4.dist-info/METADATA
odoo_addon_stock_picking_auto_create_lot_sequence-16.0.1.0.0.4.dist-info/WHEEL
odoo_addon_stock_picking_auto_create_lot_sequence-16.0.1.0.0.4.dist-info/top_level.txt
odoo_addon_stock_picking_auto_create_lot_sequence-16.0.1.0.0.4.dist-info/RECORD
