Metadata-Version: 2.1
Name: odoo-addon-stock_picking_auto_create_lot_sequence
Version: 16.0.1.0.0.4
Summary: Stock Picking Auto Create Lot Sequence
Home-page: https://github.com/OCA/stock-logistics-workflow
Author: Quartile, Odoo Community Association (OCA)
Author-email: support@odoo-community.org
License: AGPL-3
Classifier: Programming Language :: Python
Classifier: Framework :: Odoo
Classifier: Framework :: Odoo :: 16.0
Classifier: License :: OSI Approved :: GNU Affero General Public License v3
Requires-Python: >=3.10
Requires-Dist: odoo-addon-product-lot-sequence <16.1dev,>=16.0dev
Requires-Dist: odoo-addon-stock-picking-auto-create-lot <16.1dev,>=16.0dev
Requires-Dist: odoo <16.1dev,>=16.0a
